Metadata-Version: 2.1
Name: mypy-ipython
Version: 20.8.0
Summary: UNKNOWN
Home-page: https://github.com/moshez/mypy_ipython
Author: Moshe Zadka
Author-email: moshez@zadka.club
License: MIT
Project-URL: Documentation, https://mypy-ipython.readthedocs.io/en/latest/
Project-URL: Source, https://github.com/moshez/mypy_ipython
Platform: UNKNOWN
Provides-Extra: test
Provides-Extra: lint
Provides-Extra: doc
